MANIFEST.in
README.txt
plonetheme.arnolfini-configure.zcml
setup.cfg
setup.py
docs/HISTORY.txt
docs/INSTALL.txt
docs/LICENSE.GPL
docs/LICENSE.txt
plonetheme/__init__.py
plonetheme.arnolfini.egg-info/PKG-INFO
plonetheme.arnolfini.egg-info/SOURCES.txt
plonetheme.arnolfini.egg-info/dependency_links.txt
plonetheme.arnolfini.egg-info/entry_points.txt
plonetheme.arnolfini.egg-info/namespace_packages.txt
plonetheme.arnolfini.egg-info/not-zip-safe
plonetheme.arnolfini.egg-info/paster_plugins.txt
plonetheme.arnolfini.egg-info/requires.txt
plonetheme.arnolfini.egg-info/top_level.txt
plonetheme/arnolfini/__init__.py
plonetheme/arnolfini/configure.zcml
plonetheme/arnolfini/events.py
plonetheme/arnolfini/interfaces.py
plonetheme/arnolfini/permissions.py
plonetheme/arnolfini/profiles.zcml
plonetheme/arnolfini/queryoverride.py
plonetheme/arnolfini/setuphandlers.py
plonetheme/arnolfini/skins.zcml
plonetheme/arnolfini/tests.py
plonetheme/arnolfini/version.txt
plonetheme/arnolfini/browser/__init__.py
plonetheme/arnolfini/browser/blog_view.pt
plonetheme/arnolfini/browser/calendar.pt
plonetheme/arnolfini/browser/carousel_item_tile.pt
plonetheme/arnolfini/browser/collection.pt
plonetheme/arnolfini/browser/configure.zcml
plonetheme/arnolfini/browser/document_view_custom.pt
plonetheme/arnolfini/browser/event_listing.pt
plonetheme/arnolfini/browser/event_view.pt
plonetheme/arnolfini/browser/event_view_archive.pt
plonetheme/arnolfini/browser/event_view_archive_listing.pt
plonetheme/arnolfini/browser/file_view_custom.pt
plonetheme/arnolfini/browser/folder_listing_custom.pt
plonetheme/arnolfini/browser/folder_listing_threecol.pt
plonetheme/arnolfini/browser/footer_custom.pt
plonetheme/arnolfini/browser/front_page_listing.pt
plonetheme/arnolfini/browser/get_number_of_results.pt
plonetheme/arnolfini/browser/image_view_custom.pt
plonetheme/arnolfini/browser/image_view_fullscreen.pt
plonetheme/arnolfini/browser/interfaces.py
plonetheme/arnolfini/browser/link_view_custom.pt
plonetheme/arnolfini/browser/logo.pt
plonetheme/arnolfini/browser/manage_custom_portlets.pt
plonetheme/arnolfini/browser/manual_related.pt
plonetheme/arnolfini/browser/mediaShow.py
plonetheme/arnolfini/browser/mediaShow_item.pt
plonetheme/arnolfini/browser/people_listing.pt
plonetheme/arnolfini/browser/relateditems.pt
plonetheme/arnolfini/browser/search_listing.pt
plonetheme/arnolfini/browser/searchbox.pt
