Metadata-Version: 1.1
Name: plonetheme.arnolfini
Version: 0.97
Summary: An installable theme for Plone 4
Home-page: http://svn.plone.org/svn/collective/
Author: David Jonas
Author-email: david@intk.com
License: GPL
Keywords: web zope plone theme
Platform: UNKNOWN
Classifier: Framework :: Plone
Classifier: Programming Language :: Python
